{
  "total": 204212825.55,
  "end_date": "2024-09-30T00:00:00Z",
  "results": [
    {
      "id": "682449",
      "code": "0001",
      "type": "program_activity",
      "name": "MANAGEMENT AND POLICY COORDINATION",
      "amount": 89480228.42
    },
    {
      "id": "682424",
      "code": "0003",
      "type": "program_activity",
      "name": "EXPORT ENFORCEMENT",
      "amount": 63687416.94
    },
    {
      "id": "682421",
      "code": "0002",
      "type": "program_activity",
      "name": "EXPORT ADMINISTRATION",
      "amount": 49361690.11
    },
    {
      "id": "682409",
      "code": "0801",
      "type": "program_activity",
      "name": "OPERATIONS AND ADMINISTRATION (REIMBURSABLE)",
      "amount": 1323623.09
    },
    {
      "id": "602678",
      "code": "0000",
      "type": "program_activity",
      "name": "UNKNOWN/OTHER",
      "amount": 359866.99
    },
    {
      "id": "682527",
      "code": "0000",
      "type": "program_activity",
      "name": "NO PROGRAM APPLICABLE",
      "amount": 0
    }
  ]
}